{"nodes": [{"id": "c_users_nandh_desktop_khanabook_backups_khanabook_start_server_background_sh", "label": "start-server-background.sh", "file_type": "code", "source_file": "C:\\Users\\nandh\\Desktop\\Khanabook -backups\\KhanaBook\\start-server-background.sh", "source_location": "L1", "metadata": {"language": "bash", "kind": "file"}}, {"id": "c_users_nandh_desktop_khanabook_backups_khanabook_start_server_background_sh__entry", "label": "start-server-background.sh script", "file_type": "code", "source_file": "C:\\Users\\nandh\\Desktop\\Khanabook -backups\\KhanaBook\\start-server-background.sh", "source_location": "L1", "metadata": {"language": "bash", "kind": "bash_entrypoint"}}, {"id": "khanabook_start_server_background_db_url", "label": "DB_URL", "file_type": "code", "source_file": "C:\\Users\\nandh\\Desktop\\Khanabook -backups\\KhanaBook\\start-server-background.sh", "source_location": "L3", "metadata": {"language": "bash", "kind": "code"}}, {"id": "khanabook_start_server_background_db_username", "label": "DB_USERNAME", "file_type": "code", "source_file": "C:\\Users\\nandh\\Desktop\\Khanabook -backups\\KhanaBook\\start-server-background.sh", "source_location": "L4", "metadata": {"language": "bash", "kind": "code"}}, {"id": "khanabook_start_server_background_db_password", "label": "DB_PASSWORD", "file_type": "code", "source_file": "C:\\Users\\nandh\\Desktop\\Khanabook -backups\\KhanaBook\\start-server-background.sh", "source_location": "L5", "metadata": {"language": "bash", "kind": "code"}}], "edges": [{"source": "c_users_nandh_desktop_khanabook_backups_khanabook_start_server_background_sh", "target": "c_users_nandh_desktop_khanabook_backups_khanabook_start_server_background_sh__entry", "relation": "contains", "confidence": "EXTRACTED", "source_file": "C:\\Users\\nandh\\Desktop\\Khanabook -backups\\KhanaBook\\start-server-background.sh", "source_location": "L1", "weight": 1.0}, {"source": "c_users_nandh_desktop_khanabook_backups_khanabook_start_server_background_sh", "target": "khanabook_start_server_background_db_url", "relation": "defines", "confidence": "EXTRACTED", "source_file": "C:\\Users\\nandh\\Desktop\\Khanabook -backups\\KhanaBook\\start-server-background.sh", "source_location": "L3", "weight": 1.0}, {"source": "c_users_nandh_desktop_khanabook_backups_khanabook_start_server_background_sh", "target": "khanabook_start_server_background_db_username", "relation": "defines", "confidence": "EXTRACTED", "source_file": "C:\\Users\\nandh\\Desktop\\Khanabook -backups\\KhanaBook\\start-server-background.sh", "source_location": "L4", "weight": 1.0}, {"source": "c_users_nandh_desktop_khanabook_backups_khanabook_start_server_background_sh", "target": "khanabook_start_server_background_db_password", "relation": "defines", "confidence": "EXTRACTED", "source_file": "C:\\Users\\nandh\\Desktop\\Khanabook -backups\\KhanaBook\\start-server-background.sh", "source_location": "L5", "weight": 1.0}]}